LICENSE
README.rst
setup.py
mindaffectBCI/__init__.py
mindaffectBCI/config_file.py
mindaffectBCI/noisetag.py
mindaffectBCI/online_bci.py
mindaffectBCI/ssdpDiscover.py
mindaffectBCI/stimseq.py
mindaffectBCI/utopia2output.py
mindaffectBCI/utopiaController.py
mindaffectBCI/utopiaclient.py
mindaffectBCI/decoder/FileProxyHub.py
mindaffectBCI/decoder/UtopiaDataInterface.py
mindaffectBCI/decoder/__init__.py
mindaffectBCI/decoder/analyse_datasets.py
mindaffectBCI/decoder/ccaViewer.py
mindaffectBCI/decoder/dataset debugging.py
mindaffectBCI/decoder/dec_test.py
mindaffectBCI/decoder/decoder.py
mindaffectBCI/decoder/decodingCurveSupervised.py
mindaffectBCI/decoder/decodingSupervised.py
mindaffectBCI/decoder/devent2stimsequence.py
mindaffectBCI/decoder/erpViewer.py
mindaffectBCI/decoder/levelsccaViewer.py
mindaffectBCI/decoder/linear_trend_tracker.py
mindaffectBCI/decoder/lower_bound_tracker.py
mindaffectBCI/decoder/model_fitting.py
mindaffectBCI/decoder/multipleCCA.py
mindaffectBCI/decoder/multipleMCCA.py
mindaffectBCI/decoder/normalizeOutputScores.py
mindaffectBCI/decoder/normalizeOutputScores_streamed.py
mindaffectBCI/decoder/offline_analysis.py
mindaffectBCI/decoder/offline_regression_testing.py
mindaffectBCI/decoder/preprocess.py
mindaffectBCI/decoder/preprocess_transforms.py
mindaffectBCI/decoder/readCapInf.py
mindaffectBCI/decoder/scoreOutput.py
mindaffectBCI/decoder/scoreStimulus.py
mindaffectBCI/decoder/sigViewer.py
mindaffectBCI/decoder/spherical_interpolation.py
mindaffectBCI/decoder/startUtopiaHub.py
mindaffectBCI/decoder/stim2event.py
mindaffectBCI/decoder/temporal_basis.py
mindaffectBCI/decoder/timestamp_check.py
mindaffectBCI/decoder/trigger_check.py
mindaffectBCI/decoder/updateSummaryStatistics.py
mindaffectBCI/decoder/utils.py
mindaffectBCI/decoder/zscore2Ptgt_softmax.py
mindaffectBCI/decoder/offline/__init__.py
mindaffectBCI/decoder/offline/datasets.py
mindaffectBCI/decoder/offline/load_brainsonfire.py
mindaffectBCI/decoder/offline/load_brainstream.py
mindaffectBCI2.egg-info/PKG-INFO
mindaffectBCI2.egg-info/SOURCES.txt
mindaffectBCI2.egg-info/dependency_links.txt
mindaffectBCI2.egg-info/not-zip-safe
mindaffectBCI2.egg-info/requires.txt
mindaffectBCI2.egg-info/top_level.txt
